{"type":"FeatureCollection","features":[{"type":"Feature","geometry":{"type":"Point","coordinates":[14.1733417,8.6869997]},"properties":{"id":406,"nomsyndicat":"SYDECOMAR","nomdepartement":"MAYO-REY","nomcommune":"REY-BOUBA","nomlocalite":"Rey centre","latitude":"8,6869997","longitude":"14,1733417","numeroreferenceouvrage":"0","nomouvrage":"Forage lyc\u00e9e technique Rey Bouba","datecollecte":"17\/08\/2022","typeeau":"Forage","etat":"Bon","descriptionetatouvrage":null,"fontionnel":"Oui","datemiseoeuvre":"19\/01\/2019","sourcefinancement":"Guiness Cameroun","maitreouvrage":"Maire ","maitreoeuvre":"Guiness Cameroun","photourl":"https:\/\/kc.kobotoolbox.org\/media\/original?media_file=garl%2Fattachments%2Fa2dcc3b3431a4e98a6fc1cf1db96c67c%2F3333ba83-7212-44cb-b60a-5fd0c316d5d2%2F1660745285296.jpg","quantitesuffisanteeau":"Oui","qualiteeau":"Mauvaise","etateau":"Claire","descriptionautresourcepollution":null,"sourcepollution":"Autres sources","existencecomitegestion":"Oui","statutlegal":"Informel","nomcomite":"Lyc\u00e9e technique de rey","nompointfocal":"Fongang Pierre","contactpointfocal":"696114530","commentaire":null,"nomvillage":null}}]}