{"type":"FeatureCollection","features":[{"type":"Feature","geometry":{"type":"Point","coordinates":[14.1787078,8.6754364]},"properties":{"id":422,"nomsyndicat":"SYDECOMAR","nomdepartement":"MAYO-REY","nomcommune":"REY-BOUBA","nomlocalite":"Rey centre","latitude":"8,6754364","longitude":"14,1787078","numeroreferenceouvrage":null,"nomouvrage":"Latrine march\u00e9","datecollecte":"17\/08\/2022","typeeau":"Latrines","etat":"Bon","descriptionetatouvrage":null,"fontionnel":"Oui","datemiseoeuvre":"2020","sourcefinancement":"Commune Feicom","maitreouvrage":"Maire","maitreoeuvre":"Ets Adis","photourl":"https:\/\/kc.kobotoolbox.org\/media\/original?media_file=garl%2Fattachments%2Fa2dcc3b3431a4e98a6fc1cf1db96c67c%2F35fdcd20-8b9e-4f6c-997b-3899570d09d6%2F1660755326652.jpg","quantitesuffisanteeau":null,"qualiteeau":null,"etateau":null,"descriptionautresourcepollution":null,"sourcepollution":null,"existencecomitegestion":null,"statutlegal":null,"nomcomite":null,"nompointfocal":null,"contactpointfocal":null,"commentaire":null,"nomvillage":null}},{"type":"Feature","geometry":{"type":"Point","coordinates":[14.1786748,8.6753449]},"properties":{"id":423,"nomsyndicat":"SYDECOMAR","nomdepartement":"MAYO-REY","nomcommune":"REY-BOUBA","nomlocalite":"Rey centre","latitude":"8,6753449","longitude":"14,1786748","numeroreferenceouvrage":null,"nomouvrage":"Latrine march\u00e9 central","datecollecte":"17\/08\/2022","typeeau":"Latrines","etat":"Bon","descriptionetatouvrage":null,"fontionnel":"Oui","datemiseoeuvre":"2019","sourcefinancement":"Mindevel","maitreouvrage":"Commune","maitreoeuvre":"Ets inna aissatou","photourl":"https:\/\/kc.kobotoolbox.org\/media\/original?media_file=garl%2Fattachments%2Fa2dcc3b3431a4e98a6fc1cf1db96c67c%2Fe6169e4a-296d-48bd-b4c4-f87ad526ec57%2F1660755486380.jpg","quantitesuffisanteeau":null,"qualiteeau":null,"etateau":null,"descriptionautresourcepollution":null,"sourcepollution":null,"existencecomitegestion":null,"statutlegal":null,"nomcomite":null,"nompointfocal":null,"contactpointfocal":null,"commentaire":null,"nomvillage":null}},{"type":"Feature","geometry":{"type":"Point","coordinates":[14.167049,8.4050084]},"properties":{"id":884,"nomsyndicat":"SYDECOMAR","nomdepartement":"MAYO-REY","nomcommune":"TCHOLLIRE","nomlocalite":"Tchollir\u00e9 Centre","latitude":"8,4050084","longitude":"14,167049","numeroreferenceouvrage":"Non d\u00e9finie","nomouvrage":"Latrine de la grande mosqu\u00e9e","datecollecte":"20\/08\/2022","typeeau":"Latrines","etat":"Bon","descriptionetatouvrage":null,"fontionnel":"Oui","datemiseoeuvre":"2017","sourcefinancement":"Communaut\u00e9","maitreouvrage":"Maire","maitreoeuvre":"Non d\u00e9finie","photourl":"https:\/\/kc.kobotoolbox.org\/media\/original?media_file=garl%2Fattachments%2Fa2dcc3b3431a4e98a6fc1cf1db96c67c%2Fe41dac9e-d006-4398-b9ce-c70011f33d7a%2F1660994696400.jpg","quantitesuffisanteeau":null,"qualiteeau":null,"etateau":null,"descriptionautresourcepollution":null,"sourcepollution":null,"existencecomitegestion":null,"statutlegal":null,"nomcomite":null,"nompointfocal":"Non d\u00e9finie","contactpointfocal":null,"commentaire":null,"nomvillage":null}}]}