{"type":"FeatureCollection","features":[{"type":"Feature","geometry":{"type":"Point","coordinates":[13.5032771,9.3970192]},"properties":{"id":1106,"nomsyndicat":"SYNCOBE","nomdepartement":"BENOUE","nomcommune":"PITOA","nomlocalite":"GADAMAYO","latitude":"9,3970192","longitude":"13,5032771","numeroreferenceouvrage":null,"nomouvrage":"Puit de GADAMAYO","datecollecte":"20\/08\/2022","typeeau":"Puit","etat":"Endomag\u00e9","descriptionetatouvrage":null,"fontionnel":"Non","datemiseoeuvre":null,"sourcefinancement":"Commune","maitreouvrage":"Commune","maitreoeuvre":null,"photourl":"https:\/\/kc.kobotoolbox.org\/media\/original?media_file=garl%2Fattachments%2Fa2dcc3b3431a4e98a6fc1cf1db96c67c%2F7fa38afb-f7ce-437d-aca2-d1b3cd88f15d%2F1661002202475.jpg","quantitesuffisanteeau":"Non","qualiteeau":null,"etateau":null,"descriptionautresourcepollution":null,"sourcepollution":null,"existencecomitegestion":"Non","statutlegal":null,"nomcomite":null,"nompointfocal":null,"contactpointfocal":null,"commentaire":null,"nomvillage":null}},{"type":"Feature","geometry":{"type":"Point","coordinates":[13.508574,9.3929062]},"properties":{"id":1160,"nomsyndicat":"SYNCOBE","nomdepartement":"BENOUE","nomcommune":"PITOA","nomlocalite":"PITOA","latitude":"9,3929062","longitude":"13,508574","numeroreferenceouvrage":null,"nomouvrage":"Puit du quartier GUIDAMOUTOU","datecollecte":"20\/08\/2022","typeeau":"Puit","etat":"Endomag\u00e9","descriptionetatouvrage":null,"fontionnel":"Non","datemiseoeuvre":null,"sourcefinancement":"Commune","maitreouvrage":"Commune","maitreoeuvre":null,"photourl":"https:\/\/kc.kobotoolbox.org\/media\/original?media_file=garl%2Fattachments%2Fa2dcc3b3431a4e98a6fc1cf1db96c67c%2F0f154e49-7311-4c20-912b-3626f0d7efca%2F1660984167696.jpg","quantitesuffisanteeau":"Oui","qualiteeau":"Bonne","etateau":"Claire","descriptionautresourcepollution":null,"sourcepollution":null,"existencecomitegestion":"Oui","statutlegal":"Formel","nomcomite":null,"nompointfocal":"Mr DANIEL","contactpointfocal":null,"commentaire":null,"nomvillage":null}},{"type":"Feature","geometry":{"type":"Point","coordinates":[13.5221912,9.3915636]},"properties":{"id":1202,"nomsyndicat":"SYNCOBE","nomdepartement":"BENOUE","nomcommune":"PITOA","nomlocalite":"WAFANGO","latitude":"9,3915636","longitude":"13,5221912","numeroreferenceouvrage":null,"nomouvrage":"Puit de l' EP WAFANGO","datecollecte":"20\/08\/2022","typeeau":"Puit","etat":"Endomag\u00e9","descriptionetatouvrage":null,"fontionnel":"Non","datemiseoeuvre":null,"sourcefinancement":"Commune","maitreouvrage":"Commune","maitreoeuvre":null,"photourl":"https:\/\/kc.kobotoolbox.org\/media\/original?media_file=garl%2Fattachments%2Fa2dcc3b3431a4e98a6fc1cf1db96c67c%2Fb909f001-e037-4c65-8d77-3c1001ad690d%2F1660994211309.jpg","quantitesuffisanteeau":null,"qualiteeau":null,"etateau":null,"descriptionautresourcepollution":null,"sourcepollution":null,"existencecomitegestion":"Oui","statutlegal":"Formel","nomcomite":"APEE","nompointfocal":null,"contactpointfocal":null,"commentaire":null,"nomvillage":null}}]}