{"type":"FeatureCollection","features":[{"type":"Feature","geometry":{"type":"Point","coordinates":[13.5056874,9.0170584]},"properties":{"id":206,"nomsyndicat":"SYNCOBE","nomdepartement":"BENOUE","nomcommune":"NGONG","nomlocalite":"Quartier Tchatchara","latitude":"9,0170584","longitude":"13,5056874","numeroreferenceouvrage":"N-083","nomouvrage":"Pompe de Tchatchara","datecollecte":"17\/08\/2022","typeeau":"Pompe","etat":"Bon","descriptionetatouvrage":null,"fontionnel":"Non","datemiseoeuvre":"23\/01\/2015","sourcefinancement":"Don japonais","maitreouvrage":"Commune","maitreoeuvre":null,"photourl":"https:\/\/kc.kobotoolbox.org\/media\/original?media_file=garl%2Fattachments%2Fa2dcc3b3431a4e98a6fc1cf1db96c67c%2F9ddc1c0b-675d-49f8-bc84-1877a59ca87a%2F1660729075046.jpg","quantitesuffisanteeau":"Non","qualiteeau":"Mauvaise","etateau":null,"descriptionautresourcepollution":null,"sourcepollution":null,"existencecomitegestion":"Non","statutlegal":null,"nomcomite":null,"nompointfocal":null,"contactpointfocal":null,"commentaire":null,"nomvillage":null}}]}