{"type":"FeatureCollection","features":[{"type":"Feature","geometry":{"type":"Point","coordinates":[13.4413615,9.2950785]},"properties":{"id":464,"nomsyndicat":"SYNCOBE","nomdepartement":"BENOUE","nomcommune":"GAROUA 3","nomlocalite":"BOKCLE","latitude":"9,2950785","longitude":"13,4413615","numeroreferenceouvrage":null,"nomouvrage":"Pompe de l'\u00e9cole bilingue","datecollecte":"18\/08\/2022","typeeau":"Pompe","etat":"Bon","descriptionetatouvrage":null,"fontionnel":"Oui","datemiseoeuvre":null,"sourcefinancement":null,"maitreouvrage":"Commune","maitreoeuvre":null,"photourl":"https:\/\/kc.kobotoolbox.org\/media\/original?media_file=garl%2Fattachments%2Fa2dcc3b3431a4e98a6fc1cf1db96c67c%2Fc6776d63-a736-48fa-b89b-c0d22dc95012%2F1660820473048.jpg","quantitesuffisanteeau":"Oui","qualiteeau":"Bonne","etateau":"Claire","descriptionautresourcepollution":"Pr\u00e9sence des m\u00e9nages \u0155 moins de 30 m","sourcepollution":"Existence des latrines \u0155 moins de 30 M\u010dtres ","existencecomitegestion":"Oui","statutlegal":"Informel","nomcomite":null,"nompointfocal":null,"contactpointfocal":null,"commentaire":null,"nomvillage":null}},{"type":"Feature","geometry":{"type":"Point","coordinates":[13.4408006,9.2993849]},"properties":{"id":468,"nomsyndicat":"SYNCOBE","nomdepartement":"BENOUE","nomcommune":"GAROUA 3","nomlocalite":"BOKCLE","latitude":"9,2993849","longitude":"13,4408006","numeroreferenceouvrage":null,"nomouvrage":"Pompe de BOKCLE LAHESSON","datecollecte":"18\/08\/2022","typeeau":"Pompe","etat":"Bon","descriptionetatouvrage":null,"fontionnel":"Oui","datemiseoeuvre":null,"sourcefinancement":"CARE INTERNATIONAL ET L'UE","maitreouvrage":"Commune","maitreoeuvre":null,"photourl":"https:\/\/kc.kobotoolbox.org\/media\/original?media_file=garl%2Fattachments%2Fa2dcc3b3431a4e98a6fc1cf1db96c67c%2F2f9ac912-0176-4a38-acab-8f4673669cae%2F1660821298291.jpg","quantitesuffisanteeau":"Oui","qualiteeau":"Bonne","etateau":"Claire","descriptionautresourcepollution":"Pr\u00e9sence des m\u00e9nages \u0155 moins de 30 m","sourcepollution":"Existence des latrines \u0155 moins de 30 M\u010dtres ","existencecomitegestion":"Oui","statutlegal":"Informel","nomcomite":null,"nompointfocal":null,"contactpointfocal":null,"commentaire":null,"nomvillage":null}},{"type":"Feature","geometry":{"type":"Point","coordinates":[13.4388546,9.2974315]},"properties":{"id":471,"nomsyndicat":"SYNCOBE","nomdepartement":"BENOUE","nomcommune":"GAROUA 3","nomlocalite":"BOKCLE","latitude":"9,2974315","longitude":"13,4388546","numeroreferenceouvrage":null,"nomouvrage":"Forage de BOKCLE","datecollecte":"18\/08\/2022","typeeau":"Pompe","etat":"Endomag\u00e9","descriptionetatouvrage":null,"fontionnel":"Non","datemiseoeuvre":"31-oct-13","sourcefinancement":"Commune","maitreouvrage":"Commune","maitreoeuvre":"ETS MOUSTAPHA ","photourl":"https:\/\/kc.kobotoolbox.org\/media\/original?media_file=garl%2Fattachments%2Fa2dcc3b3431a4e98a6fc1cf1db96c67c%2F9e215203-e237-4fab-ab79-cddd0a61dfcb%2F1660822203940.jpg","quantitesuffisanteeau":"Oui","qualiteeau":"Bonne","etateau":"Claire","descriptionautresourcepollution":null,"sourcepollution":null,"existencecomitegestion":"Oui","statutlegal":"Informel","nomcomite":null,"nompointfocal":null,"contactpointfocal":null,"commentaire":null,"nomvillage":null}},{"type":"Feature","geometry":{"type":"Point","coordinates":[13.541889,9.2631806]},"properties":{"id":709,"nomsyndicat":"SYNCOBE","nomdepartement":"BENOUE","nomcommune":"GAROUA 3","nomlocalite":"BABLA","latitude":"9,2631806","longitude":"13,541889","numeroreferenceouvrage":null,"nomouvrage":"Forage de l'\u00e9glise catholique","datecollecte":"19\/08\/2022","typeeau":"Pompe","etat":"Bon","descriptionetatouvrage":null,"fontionnel":"Oui","datemiseoeuvre":null,"sourcefinancement":"Eglise catholique","maitreouvrage":"Eglise catholique","maitreoeuvre":null,"photourl":"https:\/\/kc.kobotoolbox.org\/media\/original?media_file=garl%2Fattachments%2Fa2dcc3b3431a4e98a6fc1cf1db96c67c%2F93b2f22c-abcb-41dd-a7be-6f4f8b754c92%2F1660913952425.jpg","quantitesuffisanteeau":"Oui","qualiteeau":"Bonne","etateau":"Claire","descriptionautresourcepollution":null,"sourcepollution":null,"existencecomitegestion":"Oui","statutlegal":"Informel","nomcomite":"Eglise catholique","nompointfocal":null,"contactpointfocal":null,"commentaire":null,"nomvillage":null}}]}