{"type":"FeatureCollection","features":[{"type":"Feature","geometry":{"type":"Point","coordinates":[13.531891,8.9830196]},"properties":{"id":1025,"nomsyndicat":"SYNCOBE","nomdepartement":"BENOUE","nomcommune":"LAGDO","nomlocalite":"Rabinga march\u00e9 ","latitude":"8,9830196","longitude":"13,531891","numeroreferenceouvrage":null,"nomouvrage":"Pompe rabinga march\u00e9 ","datecollecte":"20\/08\/2022","typeeau":"Pompe","etat":"Bon","descriptionetatouvrage":null,"fontionnel":"Oui","datemiseoeuvre":null,"sourcefinancement":null,"maitreouvrage":"Commune lagdo ","maitreoeuvre":null,"photourl":"https:\/\/kc.kobotoolbox.org\/media\/original?media_file=garl%2Fattachments%2Fa2dcc3b3431a4e98a6fc1cf1db96c67c%2F8f4fc55a-b7a7-4437-af38-916686819add%2F1661009904887.jpg","quantitesuffisanteeau":"Oui","qualiteeau":"Bonne","etateau":"Claire","descriptionautresourcepollution":null,"sourcepollution":null,"existencecomitegestion":"Non","statutlegal":null,"nomcomite":null,"nompointfocal":null,"contactpointfocal":null,"commentaire":null,"nomvillage":null}}]}