{"type":"FeatureCollection","features":[{"type":"Feature","geometry":{"type":"Point","coordinates":[13.4114606,9.3319836]},"properties":{"id":308,"nomsyndicat":"SYNCOBE","nomdepartement":"BENOUE","nomcommune":"GAROUA 2","nomlocalite":"Poumpoumre","latitude":"9,3319836","longitude":"13,4114606","numeroreferenceouvrage":null,"nomouvrage":null,"datecollecte":"17\/08\/2022","typeeau":"Forage","etat":"Bon","descriptionetatouvrage":null,"fontionnel":"Non","datemiseoeuvre":null,"sourcefinancement":"AQALAM","maitreouvrage":null,"maitreoeuvre":null,"photourl":"https:\/\/kc.kobotoolbox.org\/media\/original?media_file=garl%2Fattachments%2Fa2dcc3b3431a4e98a6fc1cf1db96c67c%2F799fb372-3e4a-4271-87df-9f9725c911a3%2F1660742202856.jpg","quantitesuffisanteeau":null,"qualiteeau":null,"etateau":null,"descriptionautresourcepollution":null,"sourcepollution":null,"existencecomitegestion":"Oui","statutlegal":"Informel","nomcomite":null,"nompointfocal":null,"contactpointfocal":null,"commentaire":null,"nomvillage":null}}]}