{"type":"FeatureCollection","features":[{"type":"Feature","geometry":{"type":"Point","coordinates":[13.9510953,9.9480155]},"properties":{"id":1036,"nomsyndicat":"SYNCOMALOU","nomdepartement":"MAYO-LOUTI","nomcommune":"GUIDER","nomlocalite":"ka\u010fgama 2 ","latitude":"9,9480155","longitude":"13,9510953","numeroreferenceouvrage":null,"nomouvrage":"Puit","datecollecte":"21\/08\/2022","typeeau":"Puit","etat":"Bon","descriptionetatouvrage":null,"fontionnel":"Oui","datemiseoeuvre":"1960","sourcefinancement":"Allemand ","maitreouvrage":null,"maitreoeuvre":null,"photourl":"https:\/\/kc.kobotoolbox.org\/media\/original?media_file=garl%2Fattachments%2Fa2dcc3b3431a4e98a6fc1cf1db96c67c%2Fa0582c90-17cf-4a5d-ace2-490b7b48f958%2F1661068023114.jpg","quantitesuffisanteeau":"Oui","qualiteeau":"Mauvaise","etateau":"Trouble","descriptionautresourcepollution":null,"sourcepollution":null,"existencecomitegestion":"Non","statutlegal":null,"nomcomite":null,"nompointfocal":null,"contactpointfocal":null,"commentaire":"la commune viens de fois nettoyer ","nomvillage":null}},{"type":"Feature","geometry":{"type":"Point","coordinates":[13.9364087,9.9546304]},"properties":{"id":1247,"nomsyndicat":"SYNCOMALOU","nomdepartement":"MAYO-LOUTI","nomcommune":"GUIDER","nomlocalite":"pr\u010ds du cetic de lamord\u00e9 ","latitude":"9,9546304","longitude":"13,9364087","numeroreferenceouvrage":null,"nomouvrage":"puit","datecollecte":"21\/08\/2022","typeeau":"Puit","etat":"Bon","descriptionetatouvrage":null,"fontionnel":"Oui","datemiseoeuvre":"2018","sourcefinancement":"fond propre haladi idrissou mahaou","maitreouvrage":"fond propre ","maitreoeuvre":"Fond propre ","photourl":"https:\/\/kc.kobotoolbox.org\/media\/original?media_file=garl%2Fattachments%2Fa2dcc3b3431a4e98a6fc1cf1db96c67c%2Fb832d19c-c159-4c75-bc5b-7a4c8bc1469e%2F1661073485848.jpg","quantitesuffisanteeau":"Non","qualiteeau":"Mauvaise","etateau":"Trouble","descriptionautresourcepollution":null,"sourcepollution":null,"existencecomitegestion":"Non","statutlegal":null,"nomcomite":null,"nompointfocal":null,"contactpointfocal":null,"commentaire":"c'est tr\u010ds salle et on l'utilise rarement","nomvillage":null}},{"type":"Feature","geometry":{"type":"Point","coordinates":[13.9385616,9.9417771]},"properties":{"id":1261,"nomsyndicat":"SYNCOMALOU","nomdepartement":"MAYO-LOUTI","nomcommune":"GUIDER","nomlocalite":"gadakorgou","latitude":"9,9417771","longitude":"13,9385616","numeroreferenceouvrage":null,"nomouvrage":"Puit","datecollecte":"21\/08\/2022","typeeau":"Puit","etat":"Bon","descriptionetatouvrage":null,"fontionnel":"Oui","datemiseoeuvre":"1954","sourcefinancement":"Allemand ","maitreouvrage":"Allemand ","maitreoeuvre":null,"photourl":"https:\/\/kc.kobotoolbox.org\/media\/original?media_file=garl%2Fattachments%2Fa2dcc3b3431a4e98a6fc1cf1db96c67c%2F3458728b-faca-468e-9f5e-2cbb0e121b61%2F1661078566485.jpg","quantitesuffisanteeau":"Non","qualiteeau":"Mauvaise","etateau":"Trouble","descriptionautresourcepollution":null,"sourcepollution":null,"existencecomitegestion":"Non","statutlegal":null,"nomcomite":null,"nompointfocal":null,"contactpointfocal":null,"commentaire":null,"nomvillage":null}}]}