{"type":"FeatureCollection","features":[{"type":"Feature","geometry":{"type":"Point","coordinates":[13.3549457,9.3038505]},"properties":{"id":94,"nomsyndicat":"SYNCOBE","nomdepartement":"BENOUE","nomcommune":"GAROUA 1","nomlocalite":"Wouro kanadi carrefour Santa Barbara ","latitude":"9,3038505","longitude":"13,3549457","numeroreferenceouvrage":null,"nomouvrage":"Forage wouro kanadi Santa Barbara ","datecollecte":"16\/08\/2022","typeeau":"Forage","etat":"Bon","descriptionetatouvrage":null,"fontionnel":"Non","datemiseoeuvre":null,"sourcefinancement":"Feicom","maitreouvrage":"Commune d'arrondissement de Garoua 1 ","maitreoeuvre":null,"photourl":"https:\/\/kc.kobotoolbox.org\/media\/original?media_file=garl%2Fattachments%2Fa2dcc3b3431a4e98a6fc1cf1db96c67c%2F32613609-4e25-4e6f-b584-a554306ced9a%2F1660661227831.jpg","quantitesuffisanteeau":"Non","qualiteeau":null,"etateau":null,"descriptionautresourcepollution":null,"sourcepollution":null,"existencecomitegestion":"Oui","statutlegal":"Formel","nomcomite":"Commune de Garoua 1","nompointfocal":null,"contactpointfocal":null,"commentaire":null,"nomvillage":null}},{"type":"Feature","geometry":{"type":"Point","coordinates":[13.4114606,9.3319836]},"properties":{"id":308,"nomsyndicat":"SYNCOBE","nomdepartement":"BENOUE","nomcommune":"GAROUA 2","nomlocalite":"Poumpoumre","latitude":"9,3319836","longitude":"13,4114606","numeroreferenceouvrage":null,"nomouvrage":null,"datecollecte":"17\/08\/2022","typeeau":"Forage","etat":"Bon","descriptionetatouvrage":null,"fontionnel":"Non","datemiseoeuvre":null,"sourcefinancement":"AQALAM","maitreouvrage":null,"maitreoeuvre":null,"photourl":"https:\/\/kc.kobotoolbox.org\/media\/original?media_file=garl%2Fattachments%2Fa2dcc3b3431a4e98a6fc1cf1db96c67c%2F799fb372-3e4a-4271-87df-9f9725c911a3%2F1660742202856.jpg","quantitesuffisanteeau":null,"qualiteeau":null,"etateau":null,"descriptionautresourcepollution":null,"sourcepollution":null,"existencecomitegestion":"Oui","statutlegal":"Informel","nomcomite":null,"nompointfocal":null,"contactpointfocal":null,"commentaire":null,"nomvillage":null}},{"type":"Feature","geometry":{"type":"Point","coordinates":[14.174263,10.0499515]},"properties":{"id":527,"nomsyndicat":"SYNCOMALOU","nomdepartement":"MAYO-LOUTI","nomcommune":"FIGUIL","nomlocalite":"march\u00e9 kong kong","latitude":"10,0499515","longitude":"14,174263","numeroreferenceouvrage":null,"nomouvrage":"Pompe \u0155 eau manuelle","datecollecte":"18\/08\/2022","typeeau":"Forage","etat":"Bon","descriptionetatouvrage":null,"fontionnel":"Non","datemiseoeuvre":null,"sourcefinancement":"commune","maitreouvrage":"Commune","maitreoeuvre":null,"photourl":"https:\/\/kc.kobotoolbox.org\/media\/original?media_file=garl%2Fattachments%2Fa2dcc3b3431a4e98a6fc1cf1db96c67c%2F2fcf68af-a506-44ce-b3a7-6627aba591e6%2F1660829844410.jpg","quantitesuffisanteeau":null,"qualiteeau":null,"etateau":null,"descriptionautresourcepollution":null,"sourcepollution":null,"existencecomitegestion":"Oui","statutlegal":"Informel","nomcomite":null,"nompointfocal":"Haman david","contactpointfocal":null,"commentaire":null,"nomvillage":null}},{"type":"Feature","geometry":{"type":"Point","coordinates":[14.1736675,8.6881119]},"properties":{"id":407,"nomsyndicat":"SYDECOMAR","nomdepartement":"MAYO-REY","nomcommune":"REY-BOUBA","nomlocalite":"Rey centre","latitude":"8,6881119","longitude":"14,1736675","numeroreferenceouvrage":"20","nomouvrage":"Forage Lyc\u00e9e bilingue de Rey Bouba","datecollecte":"17\/08\/2022","typeeau":"Forage","etat":"Bon","descriptionetatouvrage":null,"fontionnel":"Non","datemiseoeuvre":"2017","sourcefinancement":"Commune","maitreouvrage":"Maire","maitreoeuvre":"Commune","photourl":"https:\/\/kc.kobotoolbox.org\/media\/original?media_file=garl%2Fattachments%2Fa2dcc3b3431a4e98a6fc1cf1db96c67c%2F59ffb80c-a442-4cac-b7e1-604299d827c3%2F1660745900579.jpg","quantitesuffisanteeau":null,"qualiteeau":null,"etateau":null,"descriptionautresourcepollution":null,"sourcepollution":"Autres sources","existencecomitegestion":"Oui","statutlegal":"Informel","nomcomite":"Lyc\u00e9e bilingue","nompointfocal":"Ousmane Dairou","contactpointfocal":null,"commentaire":null,"nomvillage":null}}]}