{"type":"FeatureCollection","features":[{"type":"Feature","geometry":{"type":"Point","coordinates":[13.4330779,9.3009794]},"properties":{"id":668,"nomsyndicat":"SYNCOBE","nomdepartement":"BENOUE","nomcommune":"GAROUA 3","nomlocalite":"BOKLE","latitude":"9,3009794","longitude":"13,4330779","numeroreferenceouvrage":null,"nomouvrage":"Forage du restaurant m'ont des oliviers","datecollecte":"19\/08\/2022","typeeau":"Forage","etat":"Endomag\u00e9","descriptionetatouvrage":null,"fontionnel":"Oui","datemiseoeuvre":null,"sourcefinancement":null,"maitreouvrage":"Commune","maitreoeuvre":null,"photourl":"https:\/\/kc.kobotoolbox.org\/media\/original?media_file=garl%2Fattachments%2Fa2dcc3b3431a4e98a6fc1cf1db96c67c%2Fbd16e793-4d77-48c5-8991-bc56276d83bf%2F1660897715518.jpg","quantitesuffisanteeau":"Oui","qualiteeau":"Bonne","etateau":"Claire","descriptionautresourcepollution":null,"sourcepollution":null,"existencecomitegestion":"Oui","statutlegal":"Formel","nomcomite":null,"nompointfocal":"CHANTAL","contactpointfocal":"695432456","commentaire":null,"nomvillage":null}},{"type":"Feature","geometry":{"type":"Point","coordinates":[13.4959463,9.208548]},"properties":{"id":1076,"nomsyndicat":"SYNCOBE","nomdepartement":"BENOUE","nomcommune":"GAROUA 3","nomlocalite":"SANGUERE NGAL","latitude":"9,208548","longitude":"13,4959463","numeroreferenceouvrage":null,"nomouvrage":"Forage de SANGUERE NGAL","datecollecte":"19\/08\/2022","typeeau":"Forage","etat":"Endomag\u00e9","descriptionetatouvrage":null,"fontionnel":"Oui","datemiseoeuvre":null,"sourcefinancement":"Commune","maitreouvrage":"Commune","maitreoeuvre":null,"photourl":"https:\/\/kc.kobotoolbox.org\/media\/original?media_file=garl%2Fattachments%2Fa2dcc3b3431a4e98a6fc1cf1db96c67c%2Febe61e46-3815-4049-8171-8771d0dd8adb%2F1661072603104.jpg","quantitesuffisanteeau":"Oui","qualiteeau":"Bonne","etateau":"Claire","descriptionautresourcepollution":null,"sourcepollution":null,"existencecomitegestion":"Oui","statutlegal":"Formel","nomcomite":null,"nompointfocal":null,"contactpointfocal":null,"commentaire":null,"nomvillage":null}},{"type":"Feature","geometry":{"type":"Point","coordinates":[13.4514193,9.2322927]},"properties":{"id":1091,"nomsyndicat":"SYNCOBE","nomdepartement":"BENOUE","nomcommune":"GAROUA 3","nomlocalite":"DJALINGO","latitude":"9,2322927","longitude":"13,4514193","numeroreferenceouvrage":null,"nomouvrage":"Forage de DJALINGO SECTEUR","datecollecte":"19\/08\/2022","typeeau":"Forage","etat":"Endomag\u00e9","descriptionetatouvrage":null,"fontionnel":"Non","datemiseoeuvre":null,"sourcefinancement":"Commune","maitreouvrage":"Commune","maitreoeuvre":null,"photourl":"https:\/\/kc.kobotoolbox.org\/media\/original?media_file=garl%2Fattachments%2Fa2dcc3b3431a4e98a6fc1cf1db96c67c%2F065e7cb4-a75d-45ea-897e-3c8de7cdebe9%2F1661078586106.jpg","quantitesuffisanteeau":null,"qualiteeau":null,"etateau":null,"descriptionautresourcepollution":null,"sourcepollution":null,"existencecomitegestion":"Oui","statutlegal":"Formel","nomcomite":null,"nompointfocal":null,"contactpointfocal":null,"commentaire":null,"nomvillage":null}}]}